nami/__init__.py
nami/registry.py
nami/version.py
nami/apis/__init__.py
nami/apis/app.py
nami/apis/pipeline.py
nami/apis/train.py
nami/datasets/__init__.py
nami/datasets/base_dataset.py
nami/datasets/dataset_gpt.py
nami/datasets/dataset_rm.py
nami/datasets/collate/__init__.py
nami/datasets/collate/collate_gpt.py
nami/datasets/collate/collate_rm.py
nami/datasets/transforms/__init__.py
nami/evaluation/__init__.py
nami/evaluation/metrics/__init__.py
nami/evaluation/metrics/metrics_gpt.py
nami/evaluation/metrics/metrics_rm.py
nami/hooks/__init__.py
nami/hooks/resize_token_embedding_hook.py
nami/hooks/save_pretrained_hook.py
nami/losses/__init__.py
nami/losses/cross_entropy_loss.py
nami/losses/rank_loss.py
nami/losses/utils.py
nami/models/__init__.py
nami/models/bert/__init__.py
nami/models/bert/configuration_bert.py
nami/models/bert/modeling_bert.py
nami/models/gpt2/__init__.py
nami/models/gpt2/configuration_gpt2.py
nami/models/gpt2/modeling_gpt2.py
nami/models/utils/__init__.py
nami/models/utils/base_model.py
nami/models/utils/builder.py
nami/models/utils/layers.py
nami/pipelines/__init__.py
pynami-0.0.5.dist-info/LICENSE
pynami-0.0.5.dist-info/METADATA
pynami-0.0.5.dist-info/WHEEL
pynami-0.0.5.dist-info/top_level.txt
pynami-0.0.5.dist-info/RECORD
