Metadata-Version: 2.1
Name: pynami
Version: 0.0.5
Summary: Deep Learning - Transformers
Author-email: Fei Wang <fei.comm@icloud.com>
License: MIT License
Project-URL: repository, https://github.com/Fei-Wang/opnlp
Keywords: artificial intelligence,deep learning
Classifier: Development Status :: 4 - Beta
Classifier: Intended Audience :: Developers
Classifier: Topic :: Scientific/Engineering :: Artificial Intelligence
Classifier: License :: OSI Approved :: MIT License
Classifier: Programming Language :: Python :: 3
Classifier: Operating System :: OS Independent
Requires-Python: >=3.8
License-File: LICENSE
Requires-Dist: gradio (==3.19.1)
Requires-Dist: franky (==0.0.3)
Requires-Dist: transformers (==4.26.1)
Requires-Dist: torch (==1.13.1)
Requires-Dist: numpy (==1.24.2)
Requires-Dist: seqeval (==1.2.2)
